<annotation>
	<folder>images</folder>
	<filename>33.jpg</filename>
	<path>C:\Users\Jun Feng\Desktop\commercial-detection\data_generation\images\33.jpg</path>
	<source>
		<database>Unknown</database>
	</source>
	<size>
		<width>547</width>
		<height>304</height>
		<depth>3</depth>
	</size>
	<segmented>0</segmented>
	<object>
		<name>cup</name>
		<pose>Unspecified</pose>
		<truncated>1</truncated>
		<difficult>0</difficult>
		<bndbox>
			<xmin>67</xmin>
			<ymin>1</ymin>
			<xmax>189</xmax>
			<ymax>227</ymax>
		</bndbox>
	</object>
	<object>
		<name>cup</name>
		<pose>Unspecified</pose>
		<truncated>1</truncated>
		<difficult>0</difficult>
		<bndbox>
			<xmin>283</xmin>
			<ymin>67</ymin>
			<xmax>442</xmax>
			<ymax>304</ymax>
		</bndbox>
	</object>
</annotation>
